plone.app.controlpanel-4.0.1-py2.7-nspkg.pth
plone/app/controlpanel/__init__.py
plone/app/controlpanel/configure.zcml
plone/app/controlpanel/editing.py
plone/app/controlpanel/events.py
plone/app/controlpanel/filter.py
plone/app/controlpanel/interfaces.py
plone/app/controlpanel/language.py
plone/app/controlpanel/mail.py
plone/app/controlpanel/markup.py
plone/app/controlpanel/navigation.py
plone/app/controlpanel/permissions.zcml
plone/app/controlpanel/search.py
plone/app/controlpanel/security.py
plone/app/controlpanel/site.py
plone/app/controlpanel/syndication.py
plone/app/controlpanel/types.py
plone.app.controlpanel-4.0.1.dist-info/METADATA
plone.app.controlpanel-4.0.1.dist-info/WHEEL
plone.app.controlpanel-4.0.1.dist-info/namespace_packages.txt
plone.app.controlpanel-4.0.1.dist-info/top_level.txt
plone.app.controlpanel-4.0.1.dist-info/RECORD
