Metadata-Version: 2.1
Name: plone.app.controlpanel
Version: 4.0.1
Summary: Controlpanels for Plone were moved to Products.CMFPlone.
Home-page: https://pypi.org/project/plone.app.controlpanel
Author: Plone Foundation
Author-email: plone-developers@lists.sourceforge.net
License: GPL version 2
Keywords: plone controlpanel bbb
Platform: UNKNOWN
Classifier: Development Status :: 6 - Mature
Classifier: Environment :: Web Environment
Classifier: Framework :: Plone
Classifier: Framework :: Zope2
Classifier: Framework :: Zope :: 4
Classifier: License :: OSI Approved :: GNU General Public License v2 (GPLv2)
Classifier: Operating System :: OS Independent
Classifier: Programming Language :: Python
Classifier: Programming Language :: Python :: 2.7
Requires-Dist: setuptools
Requires-Dist: Products.CMFPlone (>=5.1.9999)
Provides-Extra: test
